midirenderer-0.1.3.dist-info/METADATA
midirenderer-0.1.3.dist-info/WHEEL
midirenderer/__init__.py
midirenderer/__init__.pyi
midirenderer/py.typed
midirenderer/midirenderer.pyd
midirenderer-0.1.3.dist-info/RECORD
