Metadata-Version: 2.3
Name: midirenderer
Version: 0.1.3
Classifier: Intended Audience :: Developers
Classifier: License :: OSI Approved :: MIT License
Classifier: Programming Language :: Python :: 3 :: Only
Classifier: Programming Language :: Python :: 3.8
Classifier: Programming Language :: Python :: 3.9
Classifier: Programming Language :: Python :: 3.10
Classifier: Programming Language :: Python :: 3.11
Classifier: Programming Language :: Python :: 3.12
Classifier: Programming Language :: Python :: Implementation :: CPython
Classifier: Programming Language :: Python :: Implementation :: PyPy
Classifier: Programming Language :: Rust
Classifier: Topic :: Multimedia :: Sound/Audio :: MIDI
Classifier: Topic :: Multimedia :: Sound/Audio :: Conversion
Summary: High-performance library for rendering MIDI files to WAV and Opus formats using SoundFonts
Keywords: midi,audio,soundfont,wav,opus
Author-email: Arthur Ryzhak <ryzhakar@gmail.com>
License: MIT
Requires-Python: >=3.8
Project-URL: Homepage, https://github.com/ryzhakar/midirenderer
Project-URL: Repository, https://github.com/ryzhakar/midirenderer.git
